ipinfo_db/__init__.py
ipinfo_db/client.py
ipinfo_db/reader.py
ipinfo_db/version.py
ipinfo_db-0.0.4.dist-info/LICENSE
ipinfo_db-0.0.4.dist-info/METADATA
ipinfo_db-0.0.4.dist-info/WHEEL
ipinfo_db-0.0.4.dist-info/top_level.txt
ipinfo_db-0.0.4.dist-info/RECORD
