Metadata-Version: 2.1
Name: ipinfo-db
Version: 0.0.4
Summary: Official Python free database library for IPinfo
Home-page: https://github.com/ipinfo/python-db
Author: IPinfo
Author-email: support@ipinfo.io
License: Apache License 2.0
License-File: LICENSE
Requires-Dist: maxminddb
Requires-Dist: appdirs
